plonetheme.sunburst-1.5.5-py2.7-nspkg.pth
plonetheme/sunburst/README.rst
plonetheme/sunburst/__init__.py
plonetheme/sunburst/configure.zcml
plonetheme/sunburst/setuphandlers.py
plonetheme/sunburst/browser/__init__.py
plonetheme/sunburst/browser/configure.zcml
plonetheme/sunburst/browser/interfaces.py
plonetheme/sunburst/browser/sunburstview.py
plonetheme/sunburst/profiles/default/actions.xml
plonetheme/sunburst/profiles/default/cssregistry.xml
plonetheme/sunburst/profiles/default/metadata.xml
plonetheme/sunburst/profiles/default/skins.xml
plonetheme/sunburst/profiles/default/sunburst.txt
plonetheme/sunburst/skins/sunburst_images/pb_close.png
plonetheme/sunburst/skins/sunburst_styles/IEFixes.css
plonetheme/sunburst/skins/sunburst_styles/RTL.css
plonetheme/sunburst/skins/sunburst_styles/authoring.css
plonetheme/sunburst/skins/sunburst_styles/base.css
plonetheme/sunburst/skins/sunburst_styles/base_properties.props
plonetheme/sunburst/skins/sunburst_styles/columns.css
plonetheme/sunburst/skins/sunburst_styles/controlpanel.css
plonetheme/sunburst/skins/sunburst_styles/deprecated.css
plonetheme/sunburst/skins/sunburst_styles/forms.css
plonetheme/sunburst/skins/sunburst_styles/invisibles.css
plonetheme/sunburst/skins/sunburst_styles/kupuplone.css
plonetheme/sunburst/skins/sunburst_styles/member.css
plonetheme/sunburst/skins/sunburst_styles/mobile.css
plonetheme/sunburst/skins/sunburst_styles/navtree.css
plonetheme/sunburst/skins/sunburst_styles/ploneCustom.css.dtml
plonetheme/sunburst/skins/sunburst_styles/portlets.css
plonetheme/sunburst/skins/sunburst_styles/print.css
plonetheme/sunburst/skins/sunburst_styles/public.css
plonetheme/sunburst/skins/sunburst_styles/reset.css
plonetheme/sunburst/skins/sunburst_templates/main_template.pt
plonetheme/sunburst/tests/__init__.py
plonetheme/sunburst/tests/base.py
plonetheme/sunburst/tests/test_doctests.py
plonetheme/sunburst/tests/test_integration.py
plonetheme.sunburst-1.5.5.dist-info/METADATA
plonetheme.sunburst-1.5.5.dist-info/WHEEL
plonetheme.sunburst-1.5.5.dist-info/entry_points.txt
plonetheme.sunburst-1.5.5.dist-info/namespace_packages.txt
plonetheme.sunburst-1.5.5.dist-info/top_level.txt
plonetheme.sunburst-1.5.5.dist-info/RECORD
