Metadata-Version: 2.1
Name: plonetheme.sunburst
Version: 1.5.5
Summary: The default theme for Plone 4.
Home-page: https://pypi.org/project/plonetheme.sunburst
Author: Plone Foundation
Author-email: plone-developers@lists.sourceforge.net
License: GPL version 2
Keywords: web zope plone theme
Platform: UNKNOWN
Classifier: Development Status :: 6 - Mature
Classifier: Environment :: Web Environment
Classifier: Framework :: Plone
Classifier: Framework :: Plone :: 5.0
Classifier: Framework :: Plone :: 5.1
Classifier: Framework :: Plone :: 5.2
Classifier: Framework :: Plone :: Core
Classifier: Framework :: Zope2
Classifier: Framework :: Zope :: 4
Classifier: License :: OSI Approved :: GNU General Public License v2 (GPLv2)
Classifier: Operating System :: OS Independent
Classifier: Programming Language :: Python
Classifier: Programming Language :: Python :: 2.7
Requires-Dist: setuptools
Requires-Dist: Products.CMFCore
Requires-Dist: plone.theme
Requires-Dist: zope.component
Requires-Dist: zope.interface
Provides-Extra: test
Requires-Dist: plone.app.testing ; extra == 'test'
